kanerva_sdm/__init__.py
kanerva_sdm/_kanerva_sdm.cp314-win_amd64.pyd
kanerva_sdm/bindings.cpp
kanervasdm-1.0.1.dist-info/licenses/LICENSE
kanervasdm-1.0.1.dist-info/METADATA
kanervasdm-1.0.1.dist-info/WHEEL
kanervasdm-1.0.1.dist-info/top_level.txt
kanervasdm-1.0.1.dist-info/RECORD
