Metadata-Version: 2.4
Name: KanervaSDM
Version: 1.0.1
Summary: Sparse Distributed Memory (SDM) implementation based on Kanerva (1992)
Home-page: https://github.com/made-by-simon/KanervaSDM
Author: Simon Wong
Author-email: Simon Wong <smw2@ualberta.ca>
License: MIT
Project-URL: Homepage, https://github.com/made-by-simon/KanervaSDM
Project-URL: Bug Reports, https://github.com/made-by-simon/KanervaSDM/issues
Project-URL: Source, https://github.com/made-by-simon/KanervaSDM
Keywords: sparse distributed memory,SDM,Kanerva,neural networks,cognitive models
Classifier: Development Status :: 3 - Alpha
Classifier: Intended Audience :: Science/Research
Classifier: Topic :: Scientific/Engineering :: Artificial Intelligence
Classifier: License :: OSI Approved :: MIT License
Classifier: Programming Language :: Python :: 3
Classifier: Programming Language :: Python :: 3.7
Classifier: Programming Language :: Python :: 3.8
Classifier: Programming Language :: Python :: 3.9
Classifier: Programming Language :: Python :: 3.10
Classifier: Programming Language :: Python :: 3.11
Classifier: Programming Language :: C++
Requires-Python: >=3.7
License-File: LICENSE
Dynamic: author
Dynamic: home-page
Dynamic: license-file
Dynamic: requires-python
